{
	"id": "bd5c54d9-7724-4916-9239-39efa2e61668",
	"name": "Automated_KibanaSetupAPIs_ENV",
	"values": [
		{
			"key": "brand_name",
			"value": "none",
			"enabled": true
		},
		{
			"key": "index_pattern",
			"value": "{{env}}_{{brand_name}}$$*",
			"enabled": true
		},
		{
			"key": "env",
			"value": "dev",
			"enabled": true
		},
		{
			"key": "overwrite",
			"value": "false",
			"enabled": true
		},
		{
			"key": "ApiKey",
			"value": "",
			"enabled": true
		},
		{
			"key": "topErrorCount",
			"value": "20",
			"enabled": true
		},
		{
			"key": "topAccessLogsCount",
			"value": "30",
			"enabled": true
		},
		{
			"key": "topApiLogsCount",
			"value": "30",
			"enabled": true
		},
		{
			"key": "topUniqueErrorCount",
			"value": "20",
			"enabled": true
		},
		{
			"key": "createRaw",
			"value": "false",
			"enabled": true
		},
		{
			"key": "rawIndexPattern",
			"value": "{{brand_name}}_{{env}}-*",
			"enabled": true
		}
	],
	"_postman_variable_scope": "environment",
	"_postman_exported_at": "2021-04-27T17:22:13.786Z",
	"_postman_exported_using": "Postman/8.2.3"
}